[{"game":"BOS @ CLE","time":"","awayTeam":{"awayTeam":"BOS","winPercentage":"33%","percentage":33},"homeTeam":{"homeTeam":"CLE","winPercentage":"68%","percentage":68}},{"game":"PHI @ CIN","time":"","awayTeam":{"awayTeam":"PHI","winPercentage":"61%","percentage":61},"homeTeam":{"homeTeam":"CIN","winPercentage":"39%","percentage":39}},{"game":"MIL @ PIT","time":"","awayTeam":{"awayTeam":"MIL","winPercentage":"-","percentage":null},"homeTeam":{"homeTeam":"PIT","winPercentage":"-","percentage":null}},{"game":"LAD @ WAS","time":"","awayTeam":{"awayTeam":"LAD","winPercentage":"83%","percentage":83},"homeTeam":{"homeTeam":"WAS","winPercentage":"17%","percentage":17}},{"game":"DET @ TB","time":"","awayTeam":{"awayTeam":"DET","winPercentage":"26%","percentage":26},"homeTeam":{"homeTeam":"TB","winPercentage":"74%","percentage":74}},{"game":"OAK @ NYY","time":"","awayTeam":{"awayTeam":"OAK","winPercentage":"19%","percentage":19},"homeTeam":{"homeTeam":"NYY","winPercentage":"81%","percentage":81}},{"game":"MIA @ ATL","time":"","awayTeam":{"awayTeam":"MIA","winPercentage":"18%","percentage":18},"homeTeam":{"homeTeam":"ATL","winPercentage":"82%","percentage":82}},{"game":"HOU @ CHC","time":"","awayTeam":{"awayTeam":"HOU","winPercentage":"-","percentage":null},"homeTeam":{"homeTeam":"CHC","winPercentage":"-","percentage":null}},{"game":"TOR @ KC","time":"","awayTeam":{"awayTeam":"TOR","winPercentage":"60%","percentage":60},"homeTeam":{"homeTeam":"KC","winPercentage":"40%","percentage":40}},{"game":"CHW @ MIN","time":"","awayTeam":{"awayTeam":"CHW","winPercentage":"16%","percentage":16},"homeTeam":{"homeTeam":"MIN","winPercentage":"84%","percentage":84}},{"game":"AZ @ STL","time":"","awayTeam":{"awayTeam":"AZ","winPercentage":"nodata","percentage":0},"homeTeam":{"homeTeam":"STL","winPercentage":"nodata","percentage":0}},{"game":"SEA @ TEX","time":"","awayTeam":{"awayTeam":"SEA","winPercentage":"41%","percentage":41},"homeTeam":{"homeTeam":"TEX","winPercentage":"59%","percentage":59}},{"game":"SD @ COL","time":"","awayTeam":{"awayTeam":"SD","winPercentage":"72%","percentage":72},"homeTeam":{"homeTeam":"COL","winPercentage":"28%","percentage":28}},{"game":"BAL @ LAA","time":"","awayTeam":{"awayTeam":"BAL","winPercentage":"82%","percentage":82},"homeTeam":{"homeTeam":"LAA","winPercentage":"18%","percentage":18}},{"game":"NYM @ SF","time":"","awayTeam":{"awayTeam":"NYM","winPercentage":"42%","percentage":42},"homeTeam":{"homeTeam":"SF","winPercentage":"58%","percentage":58}}]