[{"common":{"game":"CHI Cubs @ MIL Brewers","formulaWinner":"MILBrewers","seriesWinner":"MILBrewers","nextWinners":"MILBrewers","overallWinner":"MILBrewers","overallDiff":34.97023043645381,"stdDev":3.5798869433745737,"isF5HomeWinner":"MILBrewers","isF5HomeWinnerProb":0.5907684335020547,"isHomeWinner":"MILBrewers","isHomeWinnerProb":0.7970543434656957,"isOver":"Over","isOverProb":0.6353253073641898,"date":"June30th","handicap":6,"factorDiff":17.55068658749146,"patternChances":"73%(MILBrewers)  27%(CHICubs)","sample":"wins:254 loses:92 =346","avgHandicap":"Win:4 Lost:2","factor":"5.3 Win(93%) Hand(64%) totGam:14 Index0(84%) hot%(100) IndexStreak(L-1)","FinalFactor":139.6783928270213},"compare":{"awayRow":{"team":"CHICubs","RelevingRuns":1.6352941176470588,"formulaWinPercentage":23.70241324072911,"SeriesPercentage":33.166953528399304,"NextWinningPercentage":41.70103498120161,"CurrentStreak":"L1-0","TotalPercentage":32.5148847817731,"Pitcher":"K Hendricks","CarrerEra":3.61,"CurrentEra":6.87,"SpecificEra":10.085000000000003,"PitcherWins":1,"PitcherLoses":7,"FinalEra":6.87,"AVG":0.23568482380364736,"OPS":0.5109677250853722,"OBP":0.23483333333333337,"SLG":0.5,"CoversPer":31,"totalFactor":-18.61236713480956},"homeRow":{"team":"MILBrewers","RelevingRuns":1.3095238095238095,"formulaWinPercentage":76.29758675927089,"SeriesPercentage":66.8330464716007,"NextWinningPercentage":61.4536660484811,"CurrentStreak":"W1-0","TotalPercentage":67.48511521822691,"Pitcher":"F Peralta","CarrerEra":3.86,"CurrentEra":4.03,"SpecificEra":3.6900000000000004,"PitcherWins":6,"PitcherLoses":2,"FinalEra":3.9450000000000003,"AVG":0.2597280266457787,"OPS":0.4997068048698483,"OBP":0.2536666666666667,"SLG":0.7,"CoversPer":69,"totalFactor":-1.061680547318102},"selected":{},"results":{"isHomeWinner":"MILBrewers","isF5HomeWinner":"MILBrewers","isOver":"Push"}},"calcDetails":{"factorDiff":17.55068658749146,"factorWin":93,"indexWin":84,"hotWin":100},"factorDiff":17.55068658749146,"gameFactorCompleteness":1,"agnosticPattern":"XXXXX","winsCount":254,"losesCount":92,"patternChances":73,"otherTeamChances":27,"expWinner":"home","otherTeam":"away","biggestChances":73,"sample":346,"recommendedBet":5.295506865874914,"factorDetailsWinPercenatge":92.85714285714286,"indexDataWinPercenatge":84,"indexDataHotChances":100,"decisionTakerFactor":122.12770623952984,"FinalFactor":139.6783928270213,"stringDate":"06-30"},{"common":{"game":"COL Rockies @ CHI White","formulaWinner":"CHIWhite","seriesWinner":"CHIWhite","nextWinners":"COLRockies","overallWinner":"CHIWhite","overallDiff":25.59838861423475,"stdDev":8.526031370895842,"isF5HomeWinner":"CHIWhite","isF5HomeWinnerProb":0.6711193229022956,"isHomeWinner":"CHIWhite","isHomeWinnerProb":0.8417707927693912,"isOver":"No consistent","isOverProb":0,"date":"June30th","handicap":-1,"factorDiff":13.43163583789031,"patternChances":"59%(CHIWhite)  41%(COLRockies)","sample":"wins:178 loses:122 =300","avgHandicap":"Win:4 Lost:3","factor":"4.37 Win(65%) Hand(57%) totGam:23 Index1(76%) hot%(75) IndexStreak(L-1)","FinalFactor":90.69274111410283},"compare":{"awayRow":{"team":"COLRockies","RelevingRuns":2.5060240963855422,"formulaWinPercentage":4.418126333887253,"SeriesPercentage":48.33333333333333,"NextWinningPercentage":58.170290875145085,"CurrentStreak":"W1-0","TotalPercentage":37.200805692882625,"Pitcher":"K Freeland","CarrerEra":4.5,"CurrentEra":9.55,"SpecificEra":21.68,"PitcherWins":1,"PitcherLoses":3,"FinalEra":9.55,"AVG":0.24469267392973978,"OPS":0.4677395562937731,"OBP":0.2045,"SLG":0.8333333333333334,"CoversPer":57,"totalFactor":-19.292484777705127},"homeRow":{"team":"CHIWhite","RelevingRuns":1.9069767441860466,"formulaWinPercentage":95.58187366611276,"SeriesPercentage":51.66666666666667,"NextWinningPercentage":40,"CurrentStreak":"L1-0","TotalPercentage":62.799194307117375,"Pitcher":"G Crochet","CarrerEra":2.9,"CurrentEra":3.05,"SpecificEra":3.414545454545454,"PitcherWins":4,"PitcherLoses":7,"FinalEra":2.9749999999999996,"AVG":0.2158239395294628,"OPS":0.39225764545531994,"OBP":0.21861538461538463,"SLG":0.4,"CoversPer":43,"totalFactor":-5.860848939814817},"selected":{},"results":{"isHomeWinner":"COLRockies","isF5HomeWinner":"COLRockies","isOver":"Over"}},"calcDetails":{"factorDiff":13.43163583789031,"factorWin":65,"indexWin":76,"hotWin":75},"factorDiff":13.43163583789031,"gameFactorCompleteness":1,"agnosticPattern":"XXYXX","winsCount":178,"losesCount":122,"patternChances":59,"otherTeamChances":41,"expWinner":"home","otherTeam":"away","biggestChances":59,"sample":300,"recommendedBet":4.374316358378903,"factorDetailsWinPercenatge":65.21739130434783,"indexDataWinPercenatge":76,"indexDataHotChances":75,"decisionTakerFactor":77.26110527621252,"FinalFactor":90.69274111410283,"stringDate":"06-30"},{"common":{"game":"MIA Marlins @ PHI Phillies","formulaWinner":"PHIPhillies","seriesWinner":"PHIPhillies","nextWinners":"PHIPhillies","overallWinner":"PHIPhillies","overallDiff":44.67297498954326,"stdDev":1.1043321893739828,"isF5HomeWinner":"PHIPhillies","isF5HomeWinnerProb":0.6602668555030544,"isHomeWinner":"PHIPhillies","isHomeWinnerProb":0.5601338896582981,"isOver":"Under","isOverProb":0.7009264281197602,"date":"June30th","handicap":1,"factorDiff":11.155368635527795,"patternChances":"68%(PHIPhillies)  32%(MIAMarlins)","sample":"wins:154 loses:74 =228","avgHandicap":"Win:4 Lost:2","factor":"3.8 Win(73%) Hand(59%) totGam:56 Index2(72%) hot%(25) IndexStreak(W-1)","FinalFactor":63.163290838449164},"compare":{"awayRow":{"team":"MIAMarlins","RelevingRuns":1.8928571428571428,"formulaWinPercentage":7.155769873688547,"SeriesPercentage":35.834767641996564,"NextWinningPercentage":40,"CurrentStreak":"L1-0","TotalPercentage":27.66351250522837,"Pitcher":"Y Chirinos","CarrerEra":3.99,"CurrentEra":2.7,"SpecificEra":3.2350000000000003,"PitcherWins":1,"PitcherLoses":1,"FinalEra":2.7,"AVG":0.22296790943844522,"OPS":0.4243332229939372,"OBP":0.23655555555555555,"SLG":0.625,"CoversPer":20,"totalFactor":-3.9267456689457836},"homeRow":{"team":"PHIPhillies","RelevingRuns":1.2261904761904763,"formulaWinPercentage":92.84423012631144,"SeriesPercentage":64.16523235800344,"NextWinningPercentage":60,"CurrentStreak":"W1-0","TotalPercentage":72.33648749477163,"Pitcher":"R Suarez","CarrerEra":3.16,"CurrentEra":2.01,"SpecificEra":2.216666666666667,"PitcherWins":8,"PitcherLoses":1,"FinalEra":2.01,"AVG":0.24648539644878933,"OPS":0.5438542608185466,"OBP":0.25529999999999997,"SLG":0.5,"CoversPer":80,"totalFactor":7.228622966582011},"selected":{},"results":{"isHomeWinner":"PHIPhillies","isF5HomeWinner":"MIAMarlins","isOver":"Over"}},"calcDetails":{"factorDiff":11.155368635527795,"factorWin":73,"indexWin":72,"hotWin":25},"factorDiff":11.155368635527795,"gameFactorCompleteness":1,"agnosticPattern":"XXXXX","winsCount":154,"losesCount":74,"patternChances":68,"otherTeamChances":32,"expWinner":"home","otherTeam":"away","biggestChances":68,"sample":228,"recommendedBet":3.8015536863552777,"factorDetailsWinPercenatge":73.21428571428571,"indexDataWinPercenatge":72,"indexDataHotChances":25,"decisionTakerFactor":52.00792220292137,"FinalFactor":63.163290838449164,"stringDate":"06-30"},{"common":{"game":"LA Dodgers @ SF Giants","formulaWinner":"LADodgers","seriesWinner":"LADodgers","nextWinners":"SFGiants","overallWinner":"LADodgers","overallDiff":24.722878735497353,"stdDev":1.0012143146231123,"isF5HomeWinner":"LADodgers","isF5HomeWinnerProb":0.8173227787478783,"isHomeWinner":"LADodgers","isHomeWinnerProb":0.7448802116148215,"isOver":"Over","isOverProb":0.7134599753711472,"date":"June30th","handicap":6,"factorDiff":7.743220381708612,"patternChances":"51%(LADodgers)  49%(SFGiants)","sample":"wins:90 loses:86 =176","avgHandicap":"Win:4 Lost:3","factor":"2.92 Win(57%) Hand(40%) totGam:141 Index3(65%) hot%(67) IndexStreak(W-4)","FinalFactor":39.989614537279394},"compare":{"awayRow":{"team":"LADodgers","RelevingRuns":1.3411764705882352,"formulaWinPercentage":62.1873317348228,"SeriesPercentage":88.96825396825396,"NextWinningPercentage":30.62632016280014,"CurrentStreak":"L1-0","TotalPercentage":62.36143936774868,"Pitcher":"J Paxton","CarrerEra":3.67,"CurrentEra":3.39,"SpecificEra":3.2630000000000003,"PitcherWins":7,"PitcherLoses":3,"FinalEra":3.5300000000000002,"AVG":0.26683151391092563,"OPS":0.5417733178414295,"OBP":0.316,"SLG":0,"CoversPer":76,"totalFactor":-0.5157852453231531},"homeRow":{"team":"SFGiants","RelevingRuns":2.1176470588235294,"formulaWinPercentage":37.8126682651772,"SeriesPercentage":11.031746031746039,"NextWinningPercentage":60.870970003803414,"CurrentStreak":"W1-0","TotalPercentage":37.63856063225133,"Pitcher":"R Rodriguez","CarrerEra":4.7,"CurrentEra":4.7,"SpecificEra":3.355555555555555,"PitcherWins":4,"PitcherLoses":5,"FinalEra":4.7,"AVG":0.24952401141342317,"OPS":0.5253949645126116,"OBP":0.2654444444444444,"SLG":0.625,"CoversPer":24,"totalFactor":-8.259005627031765},"selected":{},"results":{"isHomeWinner":"SFGiants","isF5HomeWinner":"SFGiants","isOver":"Over"}},"calcDetails":{"factorDiff":7.743220381708612,"factorWin":57,"indexWin":65,"hotWin":67},"factorDiff":7.743220381708612,"gameFactorCompleteness":1,"agnosticPattern":"XXYXX","winsCount":90,"losesCount":86,"patternChances":51,"otherTeamChances":49,"expWinner":"away","otherTeam":"home","biggestChances":51,"sample":176,"recommendedBet":2.917432203817086,"factorDetailsWinPercenatge":57.4468085106383,"indexDataWinPercenatge":65,"indexDataHotChances":67,"decisionTakerFactor":32.24639415557078,"FinalFactor":39.989614537279394,"stringDate":"06-30"},{"common":{"game":"WAS Nationals @ TB Rays","formulaWinner":"TBRays","seriesWinner":"WASNationals","nextWinners":"TBRays","overallWinner":"TBRays","overallDiff":24.31062931913042,"stdDev":1.6662532820672853,"isF5HomeWinner":"TBRays","isF5HomeWinnerProb":0.5247439978289787,"isHomeWinner":"TBRays","isHomeWinnerProb":0.7856949356603112,"isOver":"No consistent","isOverProb":0,"date":"June30th","handicap":5,"factorDiff":10.951783771107383,"patternChances":"62%(TBRays)  38%(WASNationals)","sample":"wins:90 loses:56 =146","avgHandicap":"Win:4 Lost:3","factor":"2.76 Win(57%) Hand(40%) totGam:141 Index4(65%) hot%(52) IndexStreak(L-3)","FinalFactor":52.8365312786936},"compare":{"awayRow":{"team":"WASNationals","RelevingRuns":1.5060240963855422,"formulaWinPercentage":19.37719818806042,"SeriesPercentage":47.00803212851406,"NextWinningPercentage":47.402399363276984,"CurrentStreak":"L1-0","TotalPercentage":37.844685340434786,"Pitcher":"P Corbin","CarrerEra":4.45,"CurrentEra":5.46,"SpecificEra":6.575000000000001,"PitcherWins":3,"PitcherLoses":7,"FinalEra":5.46,"AVG":0.2326905116971382,"OPS":0.4951836140326945,"OBP":0.2572857142857143,"SLG":0,"CoversPer":41,"totalFactor":-14.952492913396048},"homeRow":{"team":"TBRays","RelevingRuns":1.6547619047619047,"formulaWinPercentage":80.6228018119396,"SeriesPercentage":52.99196787148594,"NextWinningPercentage":53.26763833492568,"CurrentStreak":"W1-0","TotalPercentage":62.15531465956521,"Pitcher":"T Bradley","CarrerEra":5.02,"CurrentEra":3.81,"SpecificEra":3.608571428571428,"PitcherWins":4,"PitcherLoses":3,"FinalEra":3.81,"AVG":0.23716794042597608,"OPS":0.48944410320460735,"OBP":0.21055555555555558,"SLG":0.5555555555555556,"CoversPer":59,"totalFactor":-4.000709142288665},"selected":{},"results":{"isHomeWinner":"TBRays","isF5HomeWinner":"TBRays","isOver":"Under"}},"calcDetails":{"factorDiff":10.951783771107383,"factorWin":57,"indexWin":65,"hotWin":52},"factorDiff":10.951783771107383,"gameFactorCompleteness":1,"agnosticPattern":"XYXXX","winsCount":90,"losesCount":56,"patternChances":62,"otherTeamChances":38,"expWinner":"home","otherTeam":"away","biggestChances":62,"sample":146,"recommendedBet":2.7595178377110736,"factorDetailsWinPercenatge":57.4468085106383,"indexDataWinPercenatge":65,"indexDataHotChances":52,"decisionTakerFactor":41.88474750758621,"FinalFactor":52.8365312786936,"stringDate":"06-30"},{"common":{"game":"CLE Guardians @ KC Royals","formulaWinner":"KCRoyals","seriesWinner":"KCRoyals","nextWinners":"KCRoyals","overallWinner":"KCRoyals","overallDiff":55.99130297807168,"stdDev":1.8794305259947268,"isF5HomeWinner":"No consistent","isF5HomeWinnerProb":0,"isHomeWinner":"No consistent","isHomeWinnerProb":0,"isOver":"No consistent","isOverProb":0,"date":"June30th","handicap":4,"factorDiff":9.597495373726469,"patternChances":"48%(KCRoyals)  52%(CLEGuardians)","sample":"wins:70 loses:76 =146","avgHandicap":"Win:3 Lost:3","factor":"2.69 Win(61%) Hand(50%) totGam:114 Index5(65%) hot%(61) IndexStreak(L-1)","FinalFactor":46.586579298291916},"compare":{"awayRow":{"team":"CLEGuardians","RelevingRuns":1.1097560975609757,"formulaWinPercentage":4.897109158392158,"SeriesPercentage":33.0952380952381,"NextWinningPercentage":24.641064608041944,"CurrentStreak":"L1-0","TotalPercentage":22.004348510964157,"Pitcher":"L Allen","CarrerEra":4.54,"CurrentEra":5.72,"SpecificEra":5.172727272727273,"PitcherWins":6,"PitcherLoses":5,"FinalEra":5.72,"AVG":0.25338282449258054,"OPS":0.616801000490025,"OBP":0.25630000000000003,"SLG":0.25,"CoversPer":57,"totalFactor":-10.530109746457327},"homeRow":{"team":"KCRoyals","RelevingRuns":1.2674418604651163,"formulaWinPercentage":95.10289084160785,"SeriesPercentage":66.9047619047619,"NextWinningPercentage":60,"CurrentStreak":"W1-0","TotalPercentage":77.99565148903584,"Pitcher":"S Lugo","CarrerEra":3.32,"CurrentEra":2.29,"SpecificEra":1.6155555555555556,"PitcherWins":4,"PitcherLoses":5,"FinalEra":2.29,"AVG":0.24016897846985052,"OPS":0.5255094227477948,"OBP":0.25433333333333336,"SLG":0.5454545454545454,"CoversPer":43,"totalFactor":-0.9326143727308591},"selected":{},"results":{"isHomeWinner":"KCRoyals","isF5HomeWinner":"KCRoyals","isOver":"Push"}},"calcDetails":{"factorDiff":9.597495373726469,"factorWin":61,"indexWin":65,"hotWin":61},"factorDiff":9.597495373726469,"gameFactorCompleteness":1,"agnosticPattern":"XXXXZ","winsCount":70,"losesCount":76,"patternChances":48,"otherTeamChances":52,"expWinner":"home","otherTeam":"away","biggestChances":52,"sample":146,"recommendedBet":2.6859749537372646,"factorDetailsWinPercenatge":61.40350877192982,"indexDataWinPercenatge":65,"indexDataHotChances":61,"decisionTakerFactor":36.98908392456545,"FinalFactor":46.586579298291916,"stringDate":"06-30"},{"common":{"game":"CIN Reds @ STL Cardinals","formulaWinner":"STLCardinals","seriesWinner":"CINReds","nextWinners":"STLCardinals","overallWinner":"STLCardinals","overallDiff":17.002158259270374,"stdDev":0.8075121784637967,"isF5HomeWinner":"No consistent","isF5HomeWinnerProb":0,"isHomeWinner":"STLCardinals","isHomeWinnerProb":0.7353300061330197,"isOver":"Under","isOverProb":0.5121288828222448,"date":"June30th","handicap":2,"factorDiff":9.887663997039114,"patternChances":"57%(STLCardinals)  43%(CINReds)","sample":"wins:74 loses:56 =130","avgHandicap":"Win:4 Lost:3","factor":"2.58 Win(61%) Hand(50%) totGam:114 Index6(68%) hot%(71) IndexStreak(W-2)","FinalFactor":48.192821257147486},"compare":{"awayRow":{"team":"CINReds","RelevingRuns":1.7023809523809523,"formulaWinPercentage":20.4574232750868,"SeriesPercentage":66.70538133952769,"NextWinningPercentage":30.794776485338204,"CurrentStreak":"L1-0","TotalPercentage":41.49892087036481,"Pitcher":"H Greene","CarrerEra":4.39,"CurrentEra":3.79,"SpecificEra":3.57125,"PitcherWins":3,"PitcherLoses":5,"FinalEra":4.09,"AVG":0.22870331949796224,"OPS":0.5122380760773617,"OBP":0.2535,"SLG":0,"CoversPer":26,"totalFactor":-8.89986263234055},"homeRow":{"team":"STLCardinals","RelevingRuns":1.7710843373493976,"formulaWinPercentage":79.54257672491319,"SeriesPercentage":33.29461866047231,"NextWinningPercentage":53.44774988885603,"CurrentStreak":"W1-0","TotalPercentage":58.50107912963519,"Pitcher":"L Lynn","CarrerEra":3.74,"CurrentEra":3.86,"SpecificEra":3.4629999999999996,"PitcherWins":8,"PitcherLoses":2,"FinalEra":3.8,"AVG":0.2203247960205791,"OPS":0.48711770157553297,"OBP":0.2387,"SLG":0.2857142857142857,"CoversPer":74,"totalFactor":0.9878013646985635},"selected":{},"results":{"isHomeWinner":"STLCardinals","isF5HomeWinner":"STLCardinals","isOver":"Under"}},"calcDetails":{"factorDiff":9.887663997039114,"factorWin":61,"indexWin":68,"hotWin":71},"factorDiff":9.887663997039114,"gameFactorCompleteness":1,"agnosticPattern":"XYXXX","winsCount":74,"losesCount":56,"patternChances":57,"otherTeamChances":43,"expWinner":"home","otherTeam":"away","biggestChances":57,"sample":130,"recommendedBet":2.578876639970391,"factorDetailsWinPercenatge":61.40350877192982,"indexDataWinPercenatge":68,"indexDataHotChances":71,"decisionTakerFactor":38.30515726010837,"FinalFactor":48.192821257147486,"stringDate":"06-30"},{"common":{"game":"TEX Rangers @ BAL Orioles","formulaWinner":"BALOrioles","seriesWinner":"BALOrioles","nextWinners":"TEXRangers","overallWinner":"BALOrioles","overallDiff":30.010151190572913,"stdDev":1.5374621120839855,"isF5HomeWinner":"BALOrioles","isF5HomeWinnerProb":0.7474503639849006,"isHomeWinner":"BALOrioles","isHomeWinnerProb":0.8149172787600165,"isOver":"Over","isOverProb":0.5636780333731093,"date":"June30th","handicap":-9,"factorDiff":5.775507110826475,"patternChances":"43%(BALOrioles)  57%(TEXRangers)","sample":"wins:50 loses:66 =116","avgHandicap":"Win:3 Lost:3","factor":"2.46 Win(67%) Hand(45%) totGam:206 Index7(69%) hot%(59) IndexStreak(W-5)","FinalFactor":27.056848992107756},"compare":{"awayRow":{"team":"TEXRangers","RelevingRuns":1.8571428571428572,"formulaWinPercentage":26.51502615778707,"SeriesPercentage":15.188372537770135,"NextWinningPercentage":62.01011665042358,"CurrentStreak":"W1-0","TotalPercentage":34.994924404713544,"Pitcher":"A Heaney","CarrerEra":4.46,"CurrentEra":4.17,"SpecificEra":4.5,"PitcherWins":3,"PitcherLoses":7,"FinalEra":4.3149999999999995,"AVG":0.24913842060717073,"OPS":0.4899229719594049,"OBP":0.20618181818181822,"SLG":0.8461538461538461,"CoversPer":31,"totalFactor":-11.59937568844796},"homeRow":{"team":"BALOrioles","RelevingRuns":1.2619047619047619,"formulaWinPercentage":73.48497384221292,"SeriesPercentage":84.81162746222986,"NextWinningPercentage":34.35719120983113,"CurrentStreak":"L1-0","TotalPercentage":65.00507559528646,"Pitcher":"C Irvin","CarrerEra":4.31,"CurrentEra":3.74,"SpecificEra":3.968,"PitcherWins":5,"PitcherLoses":5,"FinalEra":4.025,"AVG":0.25981376680431306,"OPS":0.5745099268595508,"OBP":0.2606,"SLG":0.2857142857142857,"CoversPer":69,"totalFactor":-5.823868577621485},"selected":{},"results":{"isHomeWinner":"TEXRangers","isF5HomeWinner":"TEXRangers","isOver":"Over"}},"calcDetails":{"factorDiff":5.775507110826475,"factorWin":67,"indexWin":69,"hotWin":59},"factorDiff":5.775507110826475,"gameFactorCompleteness":1,"agnosticPattern":"XXYXX","winsCount":50,"losesCount":66,"patternChances":43,"otherTeamChances":57,"expWinner":"home","otherTeam":"away","biggestChances":57,"sample":116,"recommendedBet":2.4577550711082647,"factorDetailsWinPercenatge":67.47572815533981,"indexDataWinPercenatge":69,"indexDataHotChances":59,"decisionTakerFactor":21.281341881281282,"FinalFactor":27.056848992107756,"stringDate":"06-30"},{"common":{"game":"MIN Twins @ SEA Mariners","formulaWinner":"MINTwins","seriesWinner":"MINTwins","nextWinners":"MINTwins","overallWinner":"MINTwins","overallDiff":55.241627657408685,"stdDev":1.1569000097904143,"isF5HomeWinner":"MINTwins","isF5HomeWinnerProb":0.6354952288323856,"isHomeWinner":"MINTwins","isHomeWinnerProb":0.6653268507565284,"isOver":"Under","isOverProb":0.6076434378332555,"date":"June30th","handicap":-2,"factorDiff":5.519463102395449,"patternChances":"63%(MINTwins)  37%(SEAMariners)","sample":"wins:64 loses:38 =102","avgHandicap":"Win:3 Lost:3","factor":"2.38 Win(67%) Hand(45%) totGam:206 Index8(60%) hot%(70) IndexStreak(W-2)","FinalFactor":25.52617717306866},"compare":{"awayRow":{"team":"MINTwins","RelevingRuns":1.3333333333333333,"formulaWinPercentage":80.08432018315574,"SeriesPercentage":79.67489003633582,"NextWinningPercentage":60,"CurrentStreak":"W2-0","TotalPercentage":77.62081382870434,"Pitcher":"J Ryan","CarrerEra":3.88,"CurrentEra":3.31,"SpecificEra":3.0255555555555556,"PitcherWins":6,"PitcherLoses":3,"FinalEra":3.5949999999999998,"AVG":0.23517285181749464,"OPS":0.5109517622122663,"OBP":0.249,"SLG":0.625,"CoversPer":43,"totalFactor":-0.573297367710504},"homeRow":{"team":"SEAMariners","RelevingRuns":1.2674418604651163,"formulaWinPercentage":19.915679816844264,"SeriesPercentage":20.325109963664175,"NextWinningPercentage":23.118920531369298,"CurrentStreak":"L2-0","TotalPercentage":22.379186171295654,"Pitcher":"L Castillo","CarrerEra":3.56,"CurrentEra":3.79,"SpecificEra":4.444444444444445,"PitcherWins":5,"PitcherLoses":4,"FinalEra":3.675,"AVG":0.2182720831626953,"OPS":0.5300385822188147,"OBP":0.15576470588235294,"SLG":0.3333333333333333,"CoversPer":57,"totalFactor":-6.092760470105953},"selected":{},"results":{"isHomeWinner":"MINTwins","isF5HomeWinner":"MINTwins","isOver":"Push"}},"calcDetails":{"factorDiff":5.519463102395449,"factorWin":67,"indexWin":60,"hotWin":70},"factorDiff":5.519463102395449,"gameFactorCompleteness":1,"agnosticPattern":"XXXXX","winsCount":64,"losesCount":38,"patternChances":63,"otherTeamChances":37,"expWinner":"away","otherTeam":"home","biggestChances":63,"sample":102,"recommendedBet":2.3751946310239545,"factorDetailsWinPercenatge":67.47572815533981,"indexDataWinPercenatge":60,"indexDataHotChances":70,"decisionTakerFactor":20.006714070673212,"FinalFactor":25.52617717306866,"stringDate":"06-30"},{"common":{"game":"HOU Astros @ NY Mets","formulaWinner":"NYMets","seriesWinner":"HOUAstros","nextWinners":"HOUAstros","overallWinner":"HOUAstros","overallDiff":5.259595749793924,"stdDev":2.593120772002219,"isF5HomeWinner":"NYMets","isF5HomeWinnerProb":0.644180537558712,"isHomeWinner":"NYMets","isHomeWinnerProb":0.7708628145039067,"isOver":"Over","isOverProb":0.5798222199255454,"date":"June30th","handicap":-5,"factorDiff":13.000221786155933,"patternChances":"32%(HOUAstros)  68%(NYMets)","sample":"wins:26 loses:56 =82","avgHandicap":"Win:5 Lost:3","factor":"2.3 Win(67%) Hand(45%) totGam:206 Index9(64%) hot%(60) IndexStreak(L-1)","FinalFactor":57.39282379224103},"compare":{"awayRow":{"team":"HOUAstros","RelevingRuns":1.4216867469879517,"formulaWinPercentage":5.9092543441243155,"SeriesPercentage":79.15178571428571,"NextWinningPercentage":67.88174775421619,"CurrentStreak":"W2-0","TotalPercentage":52.62979787489696,"Pitcher":"S Dubin","CarrerEra":6.03,"CurrentEra":5.64,"SpecificEra":7.739999999999999,"PitcherWins":1,"PitcherLoses":5,"FinalEra":5.835,"AVG":0.2653652868884796,"OPS":0.47017624276660397,"OBP":0.2730000000000001,"SLG":0.6666666666666666,"CoversPer":54,"totalFactor":-15.81237919981507},"homeRow":{"team":"NYMets","RelevingRuns":1.9012345679012346,"formulaWinPercentage":94.0907456558757,"SeriesPercentage":20.848214285714292,"NextWinningPercentage":22.719383141587485,"CurrentStreak":"L2-0","TotalPercentage":47.370202125103035,"Pitcher":"L Severino","CarrerEra":3.73,"CurrentEra":3.29,"SpecificEra":3.236666666666667,"PitcherWins":5,"PitcherLoses":4,"FinalEra":3.51,"AVG":0.23649336263873305,"OPS":0.5474049612938502,"OBP":0.2290909090909091,"SLG":1,"CoversPer":46,"totalFactor":-2.812157413659136},"selected":{},"results":{"isHomeWinner":"HOUAstros","isF5HomeWinner":"HOUAstros","isOver":"Over"}},"calcDetails":{"factorDiff":13.000221786155933,"factorWin":67,"indexWin":64,"hotWin":60},"factorDiff":13.000221786155933,"gameFactorCompleteness":1,"agnosticPattern":"YXXXY","winsCount":26,"losesCount":56,"patternChances":32,"otherTeamChances":68,"expWinner":"away","otherTeam":"home","biggestChances":68,"sample":82,"recommendedBet":2.3000022178615596,"factorDetailsWinPercenatge":67.47572815533981,"indexDataWinPercenatge":64,"indexDataHotChances":60,"decisionTakerFactor":44.3926020060851,"FinalFactor":57.39282379224103,"stringDate":"06-30"},{"common":{"game":"NY Yankees @ TOR Blue","formulaWinner":"TORBlue","seriesWinner":"TORBlue","nextWinners":"NYYankees","overallWinner":"TORBlue","overallDiff":26.72994938869798,"stdDev":2.257528515877485,"isF5HomeWinner":"TORBlue","isF5HomeWinnerProb":0.633717035708941,"isHomeWinner":"TORBlue","isHomeWinnerProb":0.5983331617625496,"isOver":"Over","isOverProb":0.7746797259708409,"date":"June30th","handicap":-7,"factorDiff":3.476991024960583,"patternChances":"31%(TORBlue)  69%(NYYankees)","sample":"wins:20 loses:44 =64","avgHandicap":"Win:3 Lost:2","factor":"1.93 Win(57%) Hand(34%) totGam:76 Index10(61%) hot%(87) IndexStreak(W-3)","FinalFactor":15.214580727116994},"compare":{"awayRow":{"team":"NYYankees","RelevingRuns":1.3837209302325582,"formulaWinPercentage":32.432872298719026,"SeriesPercentage":13.571428571428584,"NextWinningPercentage":60,"CurrentStreak":"W1-0","TotalPercentage":36.63502530565101,"Pitcher":"G Cole","CarrerEra":3.19,"CurrentEra":9,"SpecificEra":7.615,"PitcherWins":1,"PitcherLoses":1,"FinalEra":9,"AVG":0.24458394464063077,"OPS":0.5819549551495694,"OBP":0.24211111111111114,"SLG":0.6666666666666666,"CoversPer":62,"totalFactor":-14.639569130441476},"homeRow":{"team":"TORBlue","RelevingRuns":1.9759036144578312,"formulaWinPercentage":67.56712770128097,"SeriesPercentage":86.42857142857142,"NextWinningPercentage":29.352334236811032,"CurrentStreak":"L1-0","TotalPercentage":63.364974694348994,"Pitcher":"K Gausman","CarrerEra":3.86,"CurrentEra":4.26,"SpecificEra":5.748888888888889,"PitcherWins":2,"PitcherLoses":7,"FinalEra":4.06,"AVG":0.23066218583959558,"OPS":0.46722601361155575,"OBP":0.24650000000000002,"SLG":0.25,"CoversPer":38,"totalFactor":-11.162578105480893},"selected":{},"results":{"isHomeWinner":"NYYankees","isF5HomeWinner":"NYYankees","isOver":"Over"}},"calcDetails":{"factorDiff":3.476991024960583,"factorWin":57,"indexWin":61,"hotWin":87},"factorDiff":3.476991024960583,"gameFactorCompleteness":1,"agnosticPattern":"XXYXX","winsCount":20,"losesCount":44,"patternChances":31,"otherTeamChances":69,"expWinner":"home","otherTeam":"away","biggestChances":69,"sample":64,"recommendedBet":1.9347699102496057,"factorDetailsWinPercenatge":56.578947368421055,"indexDataWinPercenatge":61,"indexDataHotChances":87,"decisionTakerFactor":11.737589702156411,"FinalFactor":15.214580727116994,"stringDate":"06-30"},{"common":{"game":"DET Tigers @ LA Angels","formulaWinner":"LAAngels","seriesWinner":"LAAngels","nextWinners":"DETTigers","overallWinner":"LAAngels","overallDiff":29.572228936381357,"stdDev":1.3655554173288402,"isF5HomeWinner":"LAAngels","isF5HomeWinnerProb":0.654315277338842,"isHomeWinner":"LAAngels","isHomeWinnerProb":0.7359033740881105,"isOver":"Under","isOverProb":0.6627393023974075,"date":"June30th","handicap":-1,"factorDiff":3.173898106775072,"patternChances":"31%(LAAngels)  69%(DETTigers)","sample":"wins:20 loses:44 =64","avgHandicap":"Win:3 Lost:2","factor":"1.93 Win(57%) Hand(34%) totGam:76 Index11(64%) hot%(40) IndexStreak(W-1)","FinalFactor":12.491794759191572},"compare":{"awayRow":{"team":"DETTigers","RelevingRuns":1.5595238095238095,"formulaWinPercentage":12.4843086820522,"SeriesPercentage":28.333333333333343,"NextWinningPercentage":57.47127584714537,"CurrentStreak":"W1-0","TotalPercentage":35.21388553180932,"Pitcher":"C Mize","CarrerEra":4.36,"CurrentEra":4.54,"SpecificEra":4.48875,"PitcherWins":5,"PitcherLoses":3,"FinalEra":4.45,"AVG":0.2331233937358938,"OPS":0.4903569980623829,"OBP":0.21509999999999999,"SLG":0.875,"CoversPer":47,"totalFactor":-6.120617764734511},"homeRow":{"team":"LAAngels","RelevingRuns":1.9156626506024097,"formulaWinPercentage":87.51569131794781,"SeriesPercentage":71.66666666666666,"NextWinningPercentage":21.648498577476985,"CurrentStreak":"L1-0","TotalPercentage":64.78611446819068,"Pitcher":"Tyler Anderson","CarrerEra":4.19,"CurrentEra":2.63,"SpecificEra":2.254,"PitcherWins":4,"PitcherLoses":6,"FinalEra":2.63,"AVG":0.24078522488221285,"OPS":0.5169960895864509,"OBP":0.241,"SLG":0.6666666666666666,"CoversPer":53,"totalFactor":-2.946719657959439},"selected":{},"results":{"isHomeWinner":"DETTigers","isF5HomeWinner":"DETTigers","isOver":"Over"}},"calcDetails":{"factorDiff":3.173898106775072,"factorWin":57,"indexWin":64,"hotWin":40},"factorDiff":3.173898106775072,"gameFactorCompleteness":1,"agnosticPattern":"XXYXX","winsCount":20,"losesCount":44,"patternChances":31,"otherTeamChances":69,"expWinner":"home","otherTeam":"away","biggestChances":69,"sample":64,"recommendedBet":1.9317389810677508,"factorDetailsWinPercenatge":56.578947368421055,"indexDataWinPercenatge":64,"indexDataHotChances":40,"decisionTakerFactor":9.3178966524165,"FinalFactor":12.491794759191572,"stringDate":"06-30"},{"common":{"game":"OAK Athletics @ ARI Diamondbacks","formulaWinner":"OAKAthletics","seriesWinner":"OAKAthletics","nextWinners":"OAKAthletics","overallWinner":"OAKAthletics","overallDiff":31.250356236663237,"stdDev":1.2559475143453132,"isF5HomeWinner":"No consistent","isF5HomeWinnerProb":0,"isHomeWinner":"ARIDiamondbacks","isHomeWinnerProb":0.6017957361282604,"isOver":"No consistent","isOverProb":0,"date":"June30th","handicap":4,"factorDiff":6.769332572008066,"patternChances":"24%(OAKAthletics)  76%(ARIDiamondbacks)","sample":"wins:8 loses:26 =34","avgHandicap":"Win:3 Lost:4","factor":"1.74 Win(57%) Hand(34%) totGam:76 Index12(63%) hot%(62) IndexStreak(L-1)","FinalFactor":26.507281229336847},"compare":{"awayRow":{"team":"OAKAthletics","RelevingRuns":1.6627906976744187,"formulaWinPercentage":55.77687302214477,"SeriesPercentage":72.38095238095238,"NextWinningPercentage":46.12380773190787,"CurrentStreak":"L2-0","TotalPercentage":65.62517811833162,"Pitcher":"L Medina","CarrerEra":5.39,"CurrentEra":5.25,"SpecificEra":3.9800000000000004,"PitcherWins":0,"PitcherLoses":4,"FinalEra":5.32,"AVG":0.22559034363569247,"OPS":0.4473155558911372,"OBP":0.24700000000000003,"SLG":0.25,"CoversPer":29,"totalFactor":-13.028235290265389},"homeRow":{"team":"ARIDiamondbacks","RelevingRuns":1.7738095238095237,"formulaWinPercentage":44.22312697785522,"SeriesPercentage":27.61904761904762,"NextWinningPercentage":19.447483854913003,"CurrentStreak":"W2-0","TotalPercentage":34.37482188166838,"Pitcher":"B Pfaadt","CarrerEra":5.08,"CurrentEra":4.45,"SpecificEra":4.43625,"PitcherWins":5,"PitcherLoses":3,"FinalEra":4.765000000000001,"AVG":0.26292209609173894,"OPS":0.5171375251732397,"OBP":0.24683333333333338,"SLG":0.625,"CoversPer":71,"totalFactor":-6.258902718257323},"selected":{},"results":{"isHomeWinner":"ARIDiamondbacks","isF5HomeWinner":"OAKAthletics","isOver":"Under"}},"calcDetails":{"factorDiff":6.769332572008066,"factorWin":57,"indexWin":63,"hotWin":62},"factorDiff":6.769332572008066,"gameFactorCompleteness":1,"agnosticPattern":"XXXXY","winsCount":8,"losesCount":26,"patternChances":24,"otherTeamChances":76,"expWinner":"away","otherTeam":"home","biggestChances":76,"sample":34,"recommendedBet":1.7376933257200808,"factorDetailsWinPercenatge":56.578947368421055,"indexDataWinPercenatge":63,"indexDataHotChances":62,"decisionTakerFactor":19.737948657328783,"FinalFactor":26.507281229336847,"stringDate":"06-30"},{"common":{"game":"SD Padres @ BOS Red","formulaWinner":"BOSRed","seriesWinner":"SDPadres","nextWinners":"BOSRed","overallWinner":"BOSRed","overallDiff":7.708916643829099,"stdDev":1.6645405099489725,"isF5HomeWinner":"SDPadres","isF5HomeWinnerProb":0.7902453049688526,"isHomeWinner":"SDPadres","isHomeWinnerProb":0.7618300668268567,"isOver":"Over","isOverProb":0.7602286678785779,"date":"June30th","handicap":3,"factorDiff":1.3415728670708926,"patternChances":"57%(BOSRed)  43%(SDPadres)","sample":"wins:8 loses:6 =14","avgHandicap":"Win:3 Lost:2","factor":"1.72 Win(100%) Hand(100%) totGam:2 Index13(47%) hot%(60) IndexStreak(W-1)","FinalFactor":5.071145437527974},"compare":{"awayRow":{"team":"SDPadres","RelevingRuns":1.5113636363636365,"formulaWinPercentage":19.635823720292272,"SeriesPercentage":92.7312534209086,"NextWinningPercentage":22.347921498194737,"CurrentStreak":"L1-0","TotalPercentage":46.14554167808545,"Pitcher":"M Waldron","CarrerEra":3.72,"CurrentEra":3.43,"SpecificEra":4.130000000000001,"PitcherWins":4,"PitcherLoses":6,"FinalEra":3.575,"AVG":0.26737922059001606,"OPS":0.4708478547967184,"OBP":0.27914285714285714,"SLG":0.14285714285714285,"CoversPer":36,"totalFactor":-7.884803885074822},"homeRow":{"team":"BOSRed","RelevingRuns":1.5301204819277108,"formulaWinPercentage":80.36417627970773,"SeriesPercentage":7.268746579091399,"NextWinningPercentage":69.58710351283867,"CurrentStreak":"W1-0","TotalPercentage":53.85445832191455,"Pitcher":"J Winckowski","CarrerEra":4.09,"CurrentEra":3.26,"SpecificEra":3.3874999999999997,"PitcherWins":3,"PitcherLoses":5,"FinalEra":3.675,"AVG":0.24668761548908613,"OPS":0.49435240128011215,"OBP":0.2573636363636364,"SLG":0.5,"CoversPer":64,"totalFactor":-6.5432310180039295},"selected":{},"results":{"isHomeWinner":"BOSRed","isF5HomeWinner":"BOSRed","isOver":"Under"}},"calcDetails":{"factorDiff":1.3415728670708926,"factorWin":100,"indexWin":47,"hotWin":60},"factorDiff":1.3415728670708926,"gameFactorCompleteness":1,"agnosticPattern":"XYXXY","winsCount":8,"losesCount":6,"patternChances":57,"otherTeamChances":43,"expWinner":"home","otherTeam":"away","biggestChances":57,"sample":14,"recommendedBet":1.7234157286707088,"factorDetailsWinPercenatge":100,"indexDataWinPercenatge":47,"indexDataHotChances":60,"decisionTakerFactor":3.7295725704570812,"FinalFactor":5.071145437527974,"stringDate":"06-30"},{"common":{"game":"PIT Pirates @ ATL Braves","formulaWinner":"PITPirates","seriesWinner":"ATLBraves","nextWinners":"PITPirates","overallWinner":"PITPirates","overallDiff":22.48760538603066,"stdDev":2.2023245138859107,"isF5HomeWinner":"No consistent","isF5HomeWinnerProb":0,"isHomeWinner":"ATLBraves","isHomeWinnerProb":0.7375224145582892,"isOver":"No consistent","isOverProb":0,"date":"June30th","handicap":-2,"factorDiff":3.0359797210445922,"patternChances":"40%(PITPirates)  60%(ATLBraves)","sample":"wins:16 loses:24 =40","avgHandicap":"Win:3 Lost:3","factor":"1.34 Win(31%) Hand(25%) totGam:16 Index14(61%) hot%(58) IndexStreak(L-1)","FinalFactor":10.633518972958683},"compare":{"awayRow":{"team":"PITPirates","RelevingRuns":1.8072289156626506,"formulaWinPercentage":91.47620959093122,"SeriesPercentage":30.400696864111495,"NextWinningPercentage":62.13203435596427,"CurrentStreak":"W1-0","TotalPercentage":61.24380269301533,"Pitcher":"B Falter","CarrerEra":4.54,"CurrentEra":4,"SpecificEra":4.938888888888888,"PitcherWins":3,"PitcherLoses":6,"FinalEra":4.27,"AVG":0.24029105499587428,"OPS":0.46021490223297457,"OBP":0.23190909090909093,"SLG":0.6666666666666666,"CoversPer":42,"totalFactor":-9.531161934492516},"homeRow":{"team":"ATLBraves","RelevingRuns":1.146341463414634,"formulaWinPercentage":8.523790409068766,"SeriesPercentage":69.5993031358885,"NextWinningPercentage":38.32112615947945,"CurrentStreak":"L1-0","TotalPercentage":38.756197306984674,"Pitcher":"S Schwellenbach","CarrerEra":5.4,"CurrentEra":5.4,"SpecificEra":5.353333333333334,"PitcherWins":1,"PitcherLoses":2,"FinalEra":5.4,"AVG":0.2569770149227467,"OPS":0.4975356960113059,"OBP":0.22000000000000006,"SLG":0.3333333333333333,"CoversPer":58,"totalFactor":-12.567141655537108},"selected":{},"results":{"isHomeWinner":"PITPirates","isF5HomeWinner":"PITPirates","isOver":"Under"}},"calcDetails":{"factorDiff":3.0359797210445922,"factorWin":31,"indexWin":61,"hotWin":58},"factorDiff":3.0359797210445922,"gameFactorCompleteness":1,"agnosticPattern":"XYXXY","winsCount":16,"losesCount":24,"patternChances":40,"otherTeamChances":60,"expWinner":"away","otherTeam":"home","biggestChances":60,"sample":40,"recommendedBet":1.340359797210446,"factorDetailsWinPercenatge":31.25,"indexDataWinPercenatge":61,"indexDataHotChances":58,"decisionTakerFactor":7.597539251914092,"FinalFactor":10.633518972958683,"stringDate":"06-30"}]